melting.py
melt-1.0.3.dist-info/DESCRIPTION.rst
melt-1.0.3.dist-info/entry_points.txt
melt-1.0.3.dist-info/METADATA
melt-1.0.3.dist-info/metadata.json
melt-1.0.3.dist-info/RECORD
melt-1.0.3.dist-info/top_level.txt
melt-1.0.3.dist-info/WHEEL
