Metadata-Version: 2.0
Name: melt
Version: 1.0.3
Summary: A nucleotide melt temp calculator
Home-page: https://github.com/eclarke/melt
Author: Erik Clarke
Author-email: ecl@mail.med.upenn.edu
License: GPL 3
Platform: UNKNOWN
Classifier: Topic :: Scientific/Engineering :: Bio-Informatics
Classifier: Intended Audience :: Science/Research
Classifier: License :: OSI Approved :: GNU General Public License (GPL)
Classifier: Programming Language :: Python :: 2.6
Classifier: Programming Language :: Python :: 2.7
Classifier: Programming Language :: Python :: 3
